hashnak_v1/__init__.py
hashnak_v1/hash_algorithm.py
hashnak_v1-0.1.0.dist-info/METADATA
hashnak_v1-0.1.0.dist-info/WHEEL
hashnak_v1-0.1.0.dist-info/top_level.txt
hashnak_v1-0.1.0.dist-info/RECORD
